README.rst
setup.py
src/django_shorturls.egg-info/PKG-INFO
src/django_shorturls.egg-info/SOURCES.txt
src/django_shorturls.egg-info/dependency_links.txt
src/django_shorturls.egg-info/requires.txt
src/django_shorturls.egg-info/top_level.txt
src/shorturls/__init__.py
src/shorturls/baseconv.py
src/shorturls/models.py
src/shorturls/testsettings.py
src/shorturls/urls.py
src/shorturls/views.py
src/shorturls/templatetags/__init__.py
src/shorturls/templatetags/shorturl.py
src/shorturls/tests/__init__.py
src/shorturls/tests/models.py
src/shorturls/tests/test_baseconv.py
src/shorturls/tests/test_templatetag.py
src/shorturls/tests/test_views.py