Metadata-Version: 1.1
Name: django-shorturls
Version: 1.1.1
Summary: A URL shortening app for Django.
Home-page: https://github.com/bfirsh/django-shorturls
Author: Simon Willison, Jacob Kaplan-Moss
Author-email: jacob@jacobian.org
License: BSD
Platform: UNKNOWN
Classifier: Development Status :: 4 - Beta
Classifier: Framework :: Django
Classifier: Intended Audience :: Developers
Classifier: License :: OSI Approved :: BSD License
Classifier: Operating System :: OS Independent
Classifier: Programming Language :: Python
Classifier: Topic :: Internet :: WWW/HTTP
